{
  "23": "#",
  "2f": "/",
  "777d097": "/staff/michael-govan",
  "-7eed85c2": "/staff/",
  "63a5be2d": "/blogs/",
  "3f9f45dd": "#Cross",
  "40a98ecf": "#Voice",
  "20f9fa2": "#Home",
  "-30ce79bb": "#Skills",
  "159d1a5c": "https://maps.app.goo.gl/hwuSCCvvAtZGxfE88",
  "4de542d": "tel:(248)524-0050",
  "-6b0b4764": "https://app.termly.io/document/privacy-policy/5a73b723-a358-42e1-9c52-f28de85f7469",
  "2591ace4": "https://app.termly.io/document/cookie-policy/c1781975-9b42-4ba8-9609-e4c025d6059b",
  "445ab4fe": "https://app.termly.io/notify/5a73b723-a358-42e1-9c52-f28de85f7469"
}